setup.py
hello_fun/__init__.py
hello_fun/print_hello.py
hello_fun.egg-info/PKG-INFO
hello_fun.egg-info/SOURCES.txt
hello_fun.egg-info/dependency_links.txt
hello_fun.egg-info/not-zip-safe
hello_fun.egg-info/top_level.txt