Metadata-Version: 1.0
Name: hello-fun
Version: 0.3
Summary: hello fun print
Home-page: http://github.com/
Author: Hello Fun
Author-email: hello_fun@example.com
License: MIT
Platform: UNKNOWN
